torchtoolkit/__init__.py
torchtoolkit/data.py
torchtoolkit/metrics.py
torchtoolkit/sampling.py
torchtoolkit/train.py
torchtoolkit/utils.py
torchtoolkit-0.0.4.dist-info/LICENSE
torchtoolkit-0.0.4.dist-info/METADATA
torchtoolkit-0.0.4.dist-info/WHEEL
torchtoolkit-0.0.4.dist-info/top_level.txt
torchtoolkit-0.0.4.dist-info/RECORD
