Metadata-Version: 2.1
Name: torchtoolkit
Version: 0.0.4
Summary: Useful functions to use with PyTorch
Home-page: https://github.com/Natooz/TorchToolkit
Author: Nathan Fradet
License: MIT
Keywords: artificial intelligence,deep learning,transformer,nlp
Classifier: Intended Audience :: Developers
Classifier: Intended Audience :: Science/Research
Classifier: Topic :: Scientific/Engineering :: Artificial Intelligence
Classifier: Topic :: Multimedia :: Sound/Audio :: MIDI
Classifier: License :: OSI Approved :: MIT License
Classifier: Programming Language :: Python :: 3
Classifier: Programming Language :: Python :: 3.8
Classifier: Operating System :: OS Independent
License-File: LICENSE
Requires-Dist: torch (>=1.10.0)
Requires-Dist: numpy (>=1.19.0)
Requires-Dist: tqdm
